{
  "name" : "Two Characters",
  "testType" : "SINGLE",
  "input" : {
    "type" : "STANDARD",
    "fileName" : "input.txt"
  },
  "output" : {
    "type" : "STANDARD",
    "fileName" : "output.txt"
  },
  "tests" : [ {
    "input" : "10\nbeabeefeab\n",
    "output" : "5\n",
    "index" : 0,
    "active" : true
  }, {
    "input" : "28\nasdcbsdcagfsdbgdfanfghbsfdab",
    "output" : "8",
    "index" : 1,
    "active" : true
  }, {
    "input" : "28\nasvkugfiugsalddlasguifgukvsa",
    "output" : "0",
    "index" : 2,
    "active" : true
  } ],
  "location" : "src/competition",
  "vmArgs" : "-Xmx512M",
  "mainClass" : "Main",
  "taskClass" : "competition.TwoCharacters",
  "checkerClass" : "net.egork.chelper.checkers.TokenChecker",
  "checkerParameters" : "",
  "testClasses" : [ ],
  "date" : "2019.12.08",
  "contestName" : "HackerRank - Algorithms - Strings",
  "truncate" : true,
  "inputClass" : "utils.InputReader",
  "outputClass" : "utils.OutputWriter",
  "includeLocale" : false,
  "failOnOverflow" : true,
  "interactive" : false,
  "interactor" : "net.egork.chelper.tester.Interactor"
}